{
  "id": "viz/layout",
  "title": "布局",
  "description": "「布局」是可视化界面中安排元素的方式，可与项目和组织成员共享。",
  "source": "@site/docs/viz/3-layout.md",
  "sourceDirName": "viz",
  "slug": "/viz/layout",
  "permalink": "/docs/viz/layout",
  "draft": false,
  "unlisted": false,
  "tags": [],
  "version": "current",
  "lastUpdatedBy": "xiranyu",
  "lastUpdatedAt": 1741682696000,
  "sidebarPosition": 3,
  "frontMatter": {
    "sidebar_position": 3
  },
  "sidebar": "tutorialSidebar",
  "previous": {
    "title": "快速三维可视化数据",
    "permalink": "/docs/viz/use-3d-viz"
  },
  "next": {
    "title": "面板",
    "permalink": "/docs/category/panel"
  }
}